{
  "$schema": "https://developer.microsoft.com/json-schemas/fabric/item/report/definition/visualContainer/2.3.0/schema.json",
  "name": "ce994ce7209811ad6ad8",
  "position": {
    "x": 0,
    "y": 0,
    "z": 3000,
    "height": 107.14285714285715,
    "width": 640,
    "tabOrder": 1000
  },
  "visual": {
    "visualType": "textbox",
    "objects": {
      "general": [
        {
          "properties": {
            "paragraphs": [
              {
                "textRuns": [
                  {
                    "value": "The Forecast Center (Seasonality & Trends)",
                    "textStyle": {
                      "fontFamily": "Segoe UI Semibold",
                      "fontSize": "24pt",
                      "color": "#0a1f44"
                    }
                  }
                ]
              },
              {
                "textRuns": [
                  {
                    "value": ""
                  }
                ]
              },
              {
                "textRuns": [
                  {
                    "value": "Strategic Question: ",
                    "textStyle": {
                      "fontWeight": "bold",
                      "fontSize": "12pt",
                      "color": "#0a1f44"
                    }
                  },
                  {
                    "value": "When do we need to have inventory on the ground?",
                    "textStyle": {
                      "fontSize": "12pt",
                      "color": "#0a1f44"
                    }
                  }
                ]
              }
            ]
          }
        }
      ]
    },
    "drillFilterOtherVisuals": true
  }
}